banglanews/__init__.py
banglanews/prothomalo.py
banglanews-0.0.2.dist-info/METADATA
banglanews-0.0.2.dist-info/WHEEL
banglanews-0.0.2.dist-info/top_level.txt
banglanews-0.0.2.dist-info/RECORD
