Metadata-Version: 2.1
Name: banglanews
Version: 0.0.2
Summary: 'A Bengali newspaper content scraper.'
Home-page: https://github.com/neolithian/banglanews
Author: Zakir Hossain
Author-email: neolithian@msn.com
License: UNKNOWN
Project-URL: Bug Tracker, https://github.com/neolithian/banglanews/issues
Platform: UNKNOWN
Classifier: Programming Language :: Python :: 3
Classifier: License :: OSI Approved :: MIT License
Classifier: Operating System :: OS Independent
Requires-Python: >=3.6
